gcri/__init__.py
gcri/config.py
gcri/entry.py
gcri/main.py
gcri/main_planner.py
gcri/dashboard/__init__.py
gcri/dashboard/backend/__init__.py
gcri/dashboard/backend/main.py
gcri/dashboard/backend/manager.py
gcri/dashboard/backend/watcher.py
gcri/dashboard/backend/web_callbacks.py
gcri/dashboard/frontend/dist/index.html
gcri/dashboard/frontend/dist/vite.svg
gcri/dashboard/frontend/dist/assets/index-Bo2P6D3d.css
gcri/dashboard/frontend/dist/assets/index-DtjEYUiR.js
gcri/dashboard/frontend/node_modules/flatted/python/flatted.py
gcri/graphs/__init__.py
gcri/graphs/callbacks.py
gcri/graphs/gcri_unit.py
gcri/graphs/planner.py
gcri/graphs/schemas.py
gcri/graphs/states.py
gcri/templates/__init__.py
gcri/templates/active_memory.txt
gcri/templates/black_and_white_lists.json
gcri/templates/compression.txt
gcri/templates/decision.txt
gcri/templates/global_rules.txt
gcri/templates/hypothesis.txt
gcri/templates/memory.txt
gcri/templates/planner.txt
gcri/templates/reasoning.txt
gcri/templates/strategy_generator.txt
gcri/templates/verification.txt
gcri/templates/__pycache__/__init__.cpython-313.pyc
gcri/templates/__pycache__/__init__.cpython-314.pyc
gcri/tools/__init__.py
gcri/tools/cli.py
gcri/tools/utils.py
scripts/benchmark_arc_agi_1.py
scripts/benchmark_arc_agi_2.py
scripts/benchmark_bigcodebench.py
scripts/benchmark_gpqa.py
scripts/benchmark_hle.py
scripts/benchmark_humaneval.py
scripts/benchmark_livecodebench.py
scripts/benchmark_proofwriter.py
scripts/benchmark_simplebench.py
scripts/benchmark_theoremqa.py
gcri-0.1.0.dist-info/METADATA
gcri-0.1.0.dist-info/WHEEL
gcri-0.1.0.dist-info/entry_points.txt
gcri-0.1.0.dist-info/top_level.txt
gcri-0.1.0.dist-info/RECORD
