Metadata-Version: 2.4
Name: gcri
Version: 0.1.0
Summary: Graph-based Collective Reasoning Interface - A multi-branch reasoning system for LLM agents
Author: Dirac-Robot
License: MIT
Project-URL: Homepage, https://github.com/Dirac-Robot/GCRI
Project-URL: Repository, https://github.com/Dirac-Robot/GCRI
Keywords: llm,reasoning,agents,langgraph,collective-intelligence,multi-agent
Classifier: Development Status :: 3 - Alpha
Classifier: Intended Audience :: Developers
Classifier: License :: OSI Approved :: MIT License
Classifier: Programming Language :: Python :: 3
Classifier: Programming Language :: Python :: 3.12
Classifier: Programming Language :: Python :: 3.13
Classifier: Topic :: Scientific/Engineering :: Artificial Intelligence
Requires-Python: >=3.12
Requires-Dist: annotated-types>=0.7.0
Requires-Dist: anyio>=4.11.0
Requires-Dist: ato>=2.1.6
Requires-Dist: certifi>=2025.11.12
Requires-Dist: charset-normalizer>=3.4.4
Requires-Dist: distro>=1.9.0
Requires-Dist: ddgs>=9.10.0
Requires-Dist: h11>=0.16.0
Requires-Dist: httpcore>=1.0.9
Requires-Dist: httpx>=0.28.1
Requires-Dist: idna>=3.11
Requires-Dist: jiter>=0.12.0
Requires-Dist: jsonpatch>=1.33
Requires-Dist: jsonpointer>=3.0.0
Requires-Dist: langchain>=1.0.5
Requires-Dist: langchain-anthropic>=1.2.0
Requires-Dist: langchain-core>=1.1.0
Requires-Dist: langchain-google>=0.1.1
Requires-Dist: langchain-google-genai>=3.2.0
Requires-Dist: langchain-google-vertexai>=3.1.1
Requires-Dist: langchain-openai>=1.1.0
Requires-Dist: langgraph>=1.0.3
Requires-Dist: langsmith>=0.4.42
Requires-Dist: loguru>=0.7.3
Requires-Dist: numpy>=2.3.4
Requires-Dist: openai>=2.8.1
Requires-Dist: orjson>=3.11.4
Requires-Dist: ormsgpack>=1.12.0
Requires-Dist: packaging>=25.0
Requires-Dist: pydantic>=2.12.4
Requires-Dist: pydantic-core>=2.41.5
Requires-Dist: python-dotenv>=1.2.1
Requires-Dist: pyyaml>=6.0.3
Requires-Dist: regex>=2025.11.3
Requires-Dist: requests>=2.32.5
Requires-Dist: requests-toolbelt>=1.0.0
Requires-Dist: rich>=14.2.0
Requires-Dist: sniffio>=1.3.1
Requires-Dist: sqlalchemy>=2.0.44
Requires-Dist: tenacity>=9.1.2
Requires-Dist: tiktoken>=0.12.0
Requires-Dist: toml>=0.10.2
Requires-Dist: typing-extensions>=4.15.0
Requires-Dist: urllib3>=2.5.0
Requires-Dist: xxhash>=3.6.0
Requires-Dist: zstandard>=0.25.0
Requires-Dist: datasets
Requires-Dist: fastapi
Requires-Dist: uvicorn
